{
  "type": "minecraft:chest",
  "pools": [
    {
      "bonus_rolls": 0.0,
      "entries": [
        {
          "type": "minecraft:item",
          "functions": [
            {
              "add": false,
              "count": {
                "type": "minecraft:uniform",
                "max": 6.0,
                "min": 3.0
              },
              "function": "minecraft:set_count"
            }
          ],
          "name": "aether:blue_berry",
          "weight": 3
        },
        {
          "type": "minecraft:item",
          "functions": [
            {
              "add": false,
              "count": {
                "type": "minecraft:uniform",
                "max": 6.0,
                "min": 3.0
              },
              "function": "minecraft:set_count"
            }
          ],
          "name": "ancient_aether:grapes",
          "weight": 3
        },
        {
          "type": "minecraft:item",
          "functions": [
            {
              "add": false,
              "count": {
                "type": "minecraft:uniform",
                "max": 2.0,
                "min": 1.0
              },
              "function": "minecraft:set_count"
            }
          ],
          "name": "minecraft:leather",
          "weight": 3
        },
        {
          "type": "minecraft:item",
          "functions": [
            {
              "add": false,
              "count": {
                "type": "minecraft:uniform",
                "max": 2.0,
                "min": 1.0
              },
              "function": "minecraft:set_count"
            }
          ],
          "name": "minecraft:sugar",
          "weight": 3
        },
        {
          "type": "minecraft:item",
          "functions": [
            {
              "add": false,
              "count": {
                "type": "minecraft:uniform",
                "max": 2.0,
                "min": 1.0
              },
              "function": "minecraft:set_count"
            }
          ],
          "name": "aether:aechor_petal",
          "weight": 3
        },
        {
          "type": "minecraft:item",
          "functions": [
            {
              "add": false,
              "count": {
                "type": "minecraft:uniform",
                "max": 4.0,
                "min": 2.0
              },
              "function": "minecraft:set_count"
            }
          ],
          "name": "aether:enchanted_berry",
          "weight": 2
        },
        {
          "type": "minecraft:item",
          "functions": [
            {
              "add": false,
              "count": {
                "type": "minecraft:uniform",
                "max": 4.0,
                "min": 2.0
              },
              "function": "minecraft:set_count"
            }
          ],
          "name": "aether:ambrosium_shard",
          "weight": 2
        },
        {
          "type": "minecraft:item",
          "functions": [
            {
              "add": false,
              "count": {
                "type": "minecraft:uniform",
                "max": 3.0,
                "min": 1.0
              },
              "function": "minecraft:set_count"
            }
          ],
          "name": "aether:golden_amber",
          "weight": 2
        },
        {
          "type": "minecraft:item",
          "name": "aether:skyroot_bucket",
          "weight": 2
        },
        {
          "type": "minecraft:item",
          "name": "aether:skyroot_milk_bucket"
        },
        {
          "type": "minecraft:item",
          "functions": [
            {
              "add": false,
              "count": {
                "type": "minecraft:uniform",
                "max": 2.0,
                "min": 1.0
              },
              "function": "minecraft:set_count"
            }
          ],
          "name": "aether:zanite_gemstone"
        },
        {
          "type": "minecraft:item",
          "name": "aether:blue_moa_egg"
        }
      ],
      "rolls": {
        "type": "minecraft:uniform",
        "max": 12.0,
        "min": 6.0
      }
    }
  ],
  "random_sequence": "ancient_aether:chests/settlement_skyroot_generic"
}